{"execution": {"start_timestamp": "2023-08-25T00:52:35.252Z", "finish_timestamp": "2023-08-25T00:52:37.541Z"}, "runtime": {"name": "wazero", "version": "0.0.0"}, "results": [{"name": "WASI Assemblyscript tests", "duration_s": 0.50012, "failed": 0, "skipped": 0, "passed": 12, "tests": [{"name": "environ_sizes_get-multiple-variables", "executed": true, "duration_s": 0.041944026947021484, "wasi_functions": [], "failures": []}, {"name": "fd_write-to-invalid-fd", "executed": true, "duration_s": 0.041327714920043945, "wasi_functions": [], "failures": []}, {"name": "args_sizes_get-multiple-arguments", "executed": true, "duration_s": 0.040632009506225586, "wasi_functions": [], "failures": []}, {"name": "environ_get-multiple-variables", "executed": true, "duration_s": 0.04238772392272949, "wasi_functions": [], "failures": []}, {"name": "proc_exit-failure", "executed": true, "duration_s": 0.04009675979614258, "wasi_functions": [], "failures": []}, {"name": "args_sizes_get-no-arguments", "executed": true, "duration_s": 0.041225433349609375, "wasi_functions": [], "failures": []}, {"name": "args_get-multiple-arguments", "executed": true, "duration_s": 0.04232144355773926, "wasi_functions": [], "failures": []}, {"name": "random_get-non-zero-length", "executed": true, "duration_s": 0.041502952575683594, "wasi_functions": [], "failures": []}, {"name": "environ_sizes_get-no-variables", "executed": true, "duration_s": 0.040843963623046875, "wasi_functions": [], "failures": []}, {"name": "random_get-zero-length", "executed": true, "duration_s": 0.04319453239440918, "wasi_functions": [], "failures": []}, {"name": "proc_exit-success", "executed": true, "duration_s": 0.039937734603881836, "wasi_functions": [], "failures": []}, {"name": "fd_write-to-stdout", "executed": true, "duration_s": 0.041857004165649414, "wasi_functions": [], "failures": []}]}, {"name": "WASI Rust tests", "duration_s": 1.112646, "failed": 0, "skipped": 0, "passed": 12, "tests": [{"name": "clock_time_get", "executed": true, "duration_s": 0.07182693481445312, "wasi_functions": [], "failures": []}, {"name": "fd_flags_set", "executed": true, "duration_s": 0.09133410453796387, "wasi_functions": [], "failures": []}, {"name": "interesting_paths", "executed": true, "duration_s": 0.0899345874786377, "wasi_functions": [], "failures": []}, {"name": "dangling_symlink", "executed": true, "duration_s": 0.09249544143676758, "wasi_functions": [], "failures": []}, {"name": "fd_readdir", "executed": true, "duration_s": 0.1765279769897461, "wasi_functions": [], "failures": []}, {"name": "dangling_fd", "executed": true, "duration_s": 0.08876657485961914, "wasi_functions": [], "failures": []}, {"name": "fd_filestat_get", "executed": true, "duration_s": 0.07662367820739746, "wasi_functions": [], "failures": []}, {"name": "directory_seek", "executed": true, "duration_s": 0.08367371559143066, "wasi_functions": [], "failures": []}, {"name": "big_random_buf", "executed": true, "duration_s": 0.0761570930480957, "wasi_functions": [], "failures": []}, {"name": "fd_advise", "executed": true, "duration_s": 0.08962154388427734, "wasi_functions": [], "failures": []}, {"name": "close_preopen", "executed": true, "duration_s": 0.0850834846496582, "wasi_functions": [], "failures": []}, {"name": "fd_filestat_set", "executed": true, "duration_s": 0.08761215209960938, "wasi_functions": [], "failures": []}]}, {"name": "WASI C tests", "duration_s": 0.5936, "failed": 0, "skipped": 0, "passed": 11, "tests": [{"name": "fopen-with-access", "executed": true, "duration_s": 0.05510997772216797, "wasi_functions": [], "failures": []}, {"name": "clock_gettime-monotonic", "executed": true, "duration_s": 0.05002117156982422, "wasi_functions": [], "failures": []}, {"name": "clock_getres-monotonic", "executed": true, "duration_s": 0.04897642135620117, "wasi_functions": [], "failures": []}, {"name": "clock_getres-realtime", "executed": true, "duration_s": 0.04901862144470215, "wasi_functions": [], "failures": []}, {"name": "pread-with-access", "executed": true, "duration_s": 0.057962894439697266, "wasi_functions": [], "failures": []}, {"name": "lseek", "executed": true, "duration_s": 0.05849933624267578, "wasi_functions": [], "failures": []}, {"name": "fopen-with-no-access", "executed": true, "duration_s": 0.05405545234680176, "wasi_functions": [], "failures": []}, {"name": "fdopendir-with-access", "executed": true, "duration_s": 0.05842113494873047, "wasi_functions": [], "failures": []}, {"name": "stat-dev-ino", "executed": true, "duration_s": 0.05350780487060547, "wasi_functions": [], "failures": []}, {"name": "pwrite-with-access", "executed": true, "duration_s": 0.05585336685180664, "wasi_functions": [], "failures": []}, {"name": "clock_gettime-realtime", "executed": true, "duration_s": 0.0494692325592041, "wasi_functions": [], "failures": []}]}]}