{"execution": {"start_timestamp": "2023-12-03T01:00:51.195Z", "finish_timestamp": "2023-12-03T01:01:00.734Z"}, "runtime": {"name": "wazero", "version": "0.0.0"}, "results": [{"name": "WASI Assemblyscript tests", "duration_s": 0.409605, "failed": 0, "skipped": 0, "passed": 12, "tests": [{"name": "args_get-multiple-arguments", "executed": true, "duration_s": 0.03482794761657715, "wasi_functions": [], "failures": []}, {"name": "random_get-zero-length", "executed": true, "duration_s": 0.03381609916687012, "wasi_functions": [], "failures": []}, {"name": "environ_sizes_get-multiple-variables", "executed": true, "duration_s": 0.03278160095214844, "wasi_functions": [], "failures": []}, {"name": "environ_get-multiple-variables", "executed": true, "duration_s": 0.03696775436401367, "wasi_functions": [], "failures": []}, {"name": "random_get-non-zero-length", "executed": true, "duration_s": 0.033402204513549805, "wasi_functions": [], "failures": []}, {"name": "proc_exit-success", "executed": true, "duration_s": 0.0327610969543457, "wasi_functions": [], "failures": []}, {"name": "args_sizes_get-multiple-arguments", "executed": true, "duration_s": 0.03265643119812012, "wasi_functions": [], "failures": []}, {"name": "proc_exit-failure", "executed": true, "duration_s": 0.032117605209350586, "wasi_functions": [], "failures": []}, {"name": "environ_sizes_get-no-variables", "executed": true, "duration_s": 0.0325467586517334, "wasi_functions": [], "failures": []}, {"name": "fd_write-to-invalid-fd", "executed": true, "duration_s": 0.03684830665588379, "wasi_functions": [], "failures": []}, {"name": "fd_write-to-stdout", "executed": true, "duration_s": 0.034769535064697266, "wasi_functions": [], "failures": []}, {"name": "args_sizes_get-no-arguments", "executed": true, "duration_s": 0.033615827560424805, "wasi_functions": [], "failures": []}]}, {"name": "WASI Rust tests", "duration_s": 8.524683, "failed": 15, "skipped": 0, "passed": 30, "tests": [{"name": "nofollow_errors", "executed": true, "duration_s": 0.06892943382263184, "wasi_functions": [], "failures": []}, {"name": "file_unbuffered_write", "executed": true, "duration_s": 0.06482791900634766, "wasi_functions": [], "failures": []}, {"name": "remove_nonempty_directory", "executed": true, "duration_s": 0.0640099048614502, "wasi_functions": [], "failures": []}, {"name": "symlink_loop", "executed": true, "duration_s": 0.06761908531188965, "wasi_functions": [], "failures": []}, {"name": "fd_filestat_set", "executed": true, "duration_s": 0.06268668174743652, "wasi_functions": [], "failures": []}, {"name": "isatty", "executed": true, "duration_s": 0.06308317184448242, "wasi_functions": [], "failures": []}, {"name": "fd_flags_set", "executed": true, "duration_s": 0.06598782539367676, "wasi_functions": [], "failures": []}, {"name": "remove_directory_trailing_slashes", "executed": true, "duration_s": 0.06997561454772949, "wasi_functions": [], "failures": []}, {"name": "path_link", "executed": true, "duration_s": 0.42545628547668457, "wasi_functions": [], "failures": ["0 == 1"]}, {"name": "path_open_create_existing", "executed": true, "duration_s": 0.0701742172241211, "wasi_functions": [], "failures": []}, {"name": "path_open_dirfd_not_dir", "executed": true, "duration_s": 0.06275248527526855, "wasi_functions": [], "failures": []}, {"name": "overwrite_preopen", "executed": true, "duration_s": 0.39046263694763184, "wasi_functions": [], "failures": ["0 == 1"]}, {"name": "path_open_missing", "executed": true, "duration_s": 0.06751561164855957, "wasi_functions": [], "failures": []}, {"name": "path_open_preopen", "executed": true, "duration_s": 0.43207240104675293, "wasi_functions": [], "failures": ["0 == 1"]}, {"name": "fd_readdir", "executed": true, "duration_s": 0.1755990982055664, "wasi_functions": [], "failures": []}, {"name": "symlink_filestat", "executed": true, "duration_s": 0.3958408832550049, "wasi_functions": [], "failures": ["0 == 1"]}, {"name": "dir_fd_op_failures", "executed": true, "duration_s": 0.43923068046569824, "wasi_functions": [], "failures": ["0 == 1"]}, {"name": "sched_yield", "executed": true, "duration_s": 0.05553698539733887, "wasi_functions": [], "failures": []}, {"name": "directory_seek", "executed": true, "duration_s": 0.06490778923034668, "wasi_functions": [], "failures": []}, {"name": "path_open_nonblock", "executed": true, "duration_s": 0.0612485408782959, "wasi_functions": [], "failures": []}, {"name": "file_allocate", "executed": true, "duration_s": 0.06744623184204102, "wasi_functions": [], "failures": []}, {"name": "poll_oneoff_stdio", "executed": true, "duration_s": 0.6488635540008545, "wasi_functions": [], "failures": ["0 == 1"]}, {"name": "close_preopen", "executed": true, "duration_s": 0.06442785263061523, "wasi_functions": [], "failures": []}, {"name": "file_truncation", "executed": true, "duration_s": 0.06297779083251953, "wasi_functions": [], "failures": []}, {"name": "path_filestat", "executed": true, "duration_s": 0.41910815238952637, "wasi_functions": [], "failures": ["0 == 1"]}, {"name": "path_symlink_trailing_slashes", "executed": true, "duration_s": 0.43585705757141113, "wasi_functions": [], "failures": ["0 == 1"]}, {"name": "fd_fdstat_set_rights", "executed": true, "duration_s": 0.4302544593811035, "wasi_functions": [], "failures": ["0 == 1"]}, {"name": "stdio", "executed": true, "duration_s": 0.39409351348876953, "wasi_functions": [], "failures": ["0 == 1"]}, {"name": "clock_time_get", "executed": true, "duration_s": 0.05560731887817383, "wasi_functions": [], "failures": []}, {"name": "file_pread_pwrite", "executed": true, "duration_s": 0.0702676773071289, "wasi_functions": [], "failures": []}, {"name": "path_exists", "executed": true, "duration_s": 0.06363987922668457, "wasi_functions": [], "failures": []}, {"name": "interesting_paths", "executed": true, "duration_s": 0.0679476261138916, "wasi_functions": [], "failures": []}, {"name": "dangling_symlink", "executed": true, "duration_s": 0.0682992935180664, "wasi_functions": [], "failures": []}, {"name": "symlink_create", "executed": true, "duration_s": 0.39547014236450195, "wasi_functions": [], "failures": ["0 == 1"]}, {"name": "renumber", "executed": true, "duration_s": 0.39437007904052734, "wasi_functions": [], "failures": ["0 == 1"]}, {"name": "path_rename", "executed": true, "duration_s": 0.07960247993469238, "wasi_functions": [], "failures": []}, {"name": "fd_advise", "executed": true, "duration_s": 0.06728911399841309, "wasi_functions": [], "failures": []}, {"name": "path_rename_dir_trailing_slashes", "executed": true, "duration_s": 0.06460118293762207, "wasi_functions": [], "failures": []}, {"name": "dangling_fd", "executed": true, "duration_s": 0.08188557624816895, "wasi_functions": [], "failures": []}, {"name": "unlink_file_trailing_slashes", "executed": true, "duration_s": 0.10494279861450195, "wasi_functions": [], "failures": []}, {"name": "readlink", "executed": true, "duration_s": 0.402789831161499, "wasi_functions": [], "failures": ["0 == 1"]}, {"name": "big_random_buf", "executed": true, "duration_s": 0.05978250503540039, "wasi_functions": [], "failures": []}, {"name": "truncation_rights", "executed": true, "duration_s": 0.3968043327331543, "wasi_functions": [], "failures": ["0 == 1"]}, {"name": "path_open_read_write", "executed": true, "duration_s": 0.3764617443084717, "wasi_functions": [], "failures": ["0 == 1"]}, {"name": "file_seek_tell", "executed": true, "duration_s": 0.06728267669677734, "wasi_functions": [], "failures": []}]}, {"name": "WASI C tests", "duration_s": 0.540039, "failed": 1, "skipped": 0, "passed": 12, "tests": [{"name": "clock_gettime-monotonic", "executed": true, "duration_s": 0.03896522521972656, "wasi_functions": [], "failures": []}, {"name": "fdopendir-with-access", "executed": true, "duration_s": 0.04639029502868652, "wasi_functions": [], "failures": []}, {"name": "stat-dev-ino", "executed": true, "duration_s": 0.04224443435668945, "wasi_functions": [], "failures": []}, {"name": "pwrite-with-access", "executed": true, "duration_s": 0.04391193389892578, "wasi_functions": [], "failures": []}, {"name": "sock_shutdown-invalid_fd", "executed": true, "duration_s": 0.037294864654541016, "wasi_functions": [], "failures": []}, {"name": "clock_getres-monotonic", "executed": true, "duration_s": 0.0385587215423584, "wasi_functions": [], "failures": []}, {"name": "pread-with-access", "executed": true, "duration_s": 0.04275870323181152, "wasi_functions": [], "failures": []}, {"name": "sock_shutdown-not_sock", "executed": true, "duration_s": 0.03813433647155762, "wasi_functions": [], "failures": ["0 == 1"]}, {"name": "fopen-with-access", "executed": true, "duration_s": 0.042615413665771484, "wasi_functions": [], "failures": []}, {"name": "clock_getres-realtime", "executed": true, "duration_s": 0.03999733924865723, "wasi_functions": [], "failures": []}, {"name": "fopen-with-no-access", "executed": true, "duration_s": 0.042813777923583984, "wasi_functions": [], "failures": []}, {"name": "clock_gettime-realtime", "executed": true, "duration_s": 0.03879070281982422, "wasi_functions": [], "failures": []}, {"name": "lseek", "executed": true, "duration_s": 0.04487466812133789, "wasi_functions": [], "failures": []}]}]}