{"execution": {"start_timestamp": "2024-09-24T01:11:52.602Z", "finish_timestamp": "2024-09-24T01:12:02.373Z"}, "runtime": {"name": "wazero", "version": "0.0.0"}, "results": [{"name": "WASI Assemblyscript tests", "duration_s": 0.445914, "failed": 0, "skipped": 0, "passed": 12, "tests": [{"name": "environ_get-multiple-variables", "executed": true, "duration_s": 0.039949893951416016, "wasi_functions": [], "failures": []}, {"name": "proc_exit-failure", "executed": true, "duration_s": 0.03281545639038086, "wasi_functions": [], "failures": []}, {"name": "args_get-multiple-arguments", "executed": true, "duration_s": 0.0370326042175293, "wasi_functions": [], "failures": []}, {"name": "random_get-zero-length", "executed": true, "duration_s": 0.039365291595458984, "wasi_functions": [], "failures": []}, {"name": "fd_write-to-stdout", "executed": true, "duration_s": 0.03713202476501465, "wasi_functions": [], "failures": []}, {"name": "proc_exit-success", "executed": true, "duration_s": 0.037458181381225586, "wasi_functions": [], "failures": []}, {"name": "fd_write-to-invalid-fd", "executed": true, "duration_s": 0.03403759002685547, "wasi_functions": [], "failures": []}, {"name": "environ_sizes_get-multiple-variables", "executed": true, "duration_s": 0.03620004653930664, "wasi_functions": [], "failures": []}, {"name": "random_get-non-zero-length", "executed": true, "duration_s": 0.03592658042907715, "wasi_functions": [], "failures": []}, {"name": "args_sizes_get-no-arguments", "executed": true, "duration_s": 0.03810381889343262, "wasi_functions": [], "failures": []}, {"name": "environ_sizes_get-no-variables", "executed": true, "duration_s": 0.03957724571228027, "wasi_functions": [], "failures": []}, {"name": "args_sizes_get-multiple-arguments", "executed": true, "duration_s": 0.03589582443237305, "wasi_functions": [], "failures": []}]}, {"name": "WASI Rust tests", "duration_s": 8.550975, "failed": 13, "skipped": 0, "passed": 32, "tests": [{"name": "path_rename", "executed": true, "duration_s": 0.09106278419494629, "wasi_functions": [], "failures": []}, {"name": "dangling_symlink", "executed": true, "duration_s": 0.0838766098022461, "wasi_functions": [], "failures": []}, {"name": "path_filestat", "executed": true, "duration_s": 0.44657182693481445, "wasi_functions": [], "failures": ["0 == 1"]}, {"name": "fd_fdstat_set_rights", "executed": true, "duration_s": 0.4646952152252197, "wasi_functions": [], "failures": ["0 == 1"]}, {"name": "directory_seek", "executed": true, "duration_s": 0.07981133460998535, "wasi_functions": [], "failures": []}, {"name": "stdio", "executed": true, "duration_s": 0.4143552780151367, "wasi_functions": [], "failures": ["0 == 1"]}, {"name": "symlink_filestat", "executed": true, "duration_s": 0.4163360595703125, "wasi_functions": [], "failures": ["0 == 1"]}, {"name": "path_open_preopen", "executed": true, "duration_s": 0.09056520462036133, "wasi_functions": [], "failures": []}, {"name": "path_open_missing", "executed": true, "duration_s": 0.07707381248474121, "wasi_functions": [], "failures": []}, {"name": "file_seek_tell", "executed": true, "duration_s": 0.07903623580932617, "wasi_functions": [], "failures": []}, {"name": "symlink_create", "executed": true, "duration_s": 0.42220139503479004, "wasi_functions": [], "failures": ["0 == 1"]}, {"name": "readlink", "executed": true, "duration_s": 0.43820786476135254, "wasi_functions": [], "failures": ["0 == 1"]}, {"name": "truncation_rights", "executed": true, "duration_s": 0.44718217849731445, "wasi_functions": [], "failures": ["0 == 1"]}, {"name": "renumber", "executed": true, "duration_s": 0.42652177810668945, "wasi_functions": [], "failures": ["0 == 1"]}, {"name": "file_unbuffered_write", "executed": true, "duration_s": 0.07865071296691895, "wasi_functions": [], "failures": []}, {"name": "fd_filestat_set", "executed": true, "duration_s": 0.07747173309326172, "wasi_functions": [], "failures": []}, {"name": "big_random_buf", "executed": true, "duration_s": 0.06981182098388672, "wasi_functions": [], "failures": []}, {"name": "overwrite_preopen", "executed": true, "duration_s": 0.4184427261352539, "wasi_functions": [], "failures": ["0 == 1"]}, {"name": "path_open_read_write", "executed": true, "duration_s": 0.3954188823699951, "wasi_functions": [], "failures": ["0 == 1"]}, {"name": "clock_time_get", "executed": true, "duration_s": 0.0708918571472168, "wasi_functions": [], "failures": []}, {"name": "remove_directory_trailing_slashes", "executed": true, "duration_s": 0.08350920677185059, "wasi_functions": [], "failures": []}, {"name": "dangling_fd", "executed": true, "duration_s": 0.08341550827026367, "wasi_functions": [], "failures": []}, {"name": "path_open_create_existing", "executed": true, "duration_s": 0.07860231399536133, "wasi_functions": [], "failures": []}, {"name": "symlink_loop", "executed": true, "duration_s": 0.08100295066833496, "wasi_functions": [], "failures": []}, {"name": "fd_advise", "executed": true, "duration_s": 0.08294343948364258, "wasi_functions": [], "failures": []}, {"name": "remove_nonempty_directory", "executed": true, "duration_s": 0.07758450508117676, "wasi_functions": [], "failures": []}, {"name": "file_allocate", "executed": true, "duration_s": 0.08233475685119629, "wasi_functions": [], "failures": []}, {"name": "path_symlink_trailing_slashes", "executed": true, "duration_s": 0.0895998477935791, "wasi_functions": [], "failures": []}, {"name": "path_link", "executed": true, "duration_s": 0.448941707611084, "wasi_functions": [], "failures": ["0 == 1"]}, {"name": "file_pread_pwrite", "executed": true, "duration_s": 0.0900871753692627, "wasi_functions": [], "failures": []}, {"name": "path_exists", "executed": true, "duration_s": 0.0789647102355957, "wasi_functions": [], "failures": []}, {"name": "path_rename_dir_trailing_slashes", "executed": true, "duration_s": 0.07771730422973633, "wasi_functions": [], "failures": []}, {"name": "fd_flags_set", "executed": true, "duration_s": 0.0791165828704834, "wasi_functions": [], "failures": []}, {"name": "path_open_nonblock", "executed": true, "duration_s": 0.07622623443603516, "wasi_functions": [], "failures": []}, {"name": "file_truncation", "executed": true, "duration_s": 0.07795476913452148, "wasi_functions": [], "failures": []}, {"name": "nofollow_errors", "executed": true, "duration_s": 0.08126378059387207, "wasi_functions": [], "failures": []}, {"name": "poll_oneoff_stdio", "executed": true, "duration_s": 0.675529956817627, "wasi_functions": [], "failures": ["0 == 1"]}, {"name": "sched_yield", "executed": true, "duration_s": 0.06644392013549805, "wasi_functions": [], "failures": []}, {"name": "fd_readdir", "executed": true, "duration_s": 0.16129636764526367, "wasi_functions": [], "failures": []}, {"name": "dir_fd_op_failures", "executed": true, "duration_s": 0.4592428207397461, "wasi_functions": [], "failures": ["0 == 1"]}, {"name": "path_open_dirfd_not_dir", "executed": true, "duration_s": 0.08123207092285156, "wasi_functions": [], "failures": []}, {"name": "interesting_paths", "executed": true, "duration_s": 0.08191180229187012, "wasi_functions": [], "failures": []}, {"name": "close_preopen", "executed": true, "duration_s": 0.08773279190063477, "wasi_functions": [], "failures": []}, {"name": "isatty", "executed": true, "duration_s": 0.07792234420776367, "wasi_functions": [], "failures": []}, {"name": "unlink_file_trailing_slashes", "executed": true, "duration_s": 0.08775496482849121, "wasi_functions": [], "failures": []}]}, {"name": "WASI C tests", "duration_s": 0.709078, "failed": 1, "skipped": 0, "passed": 12, "tests": [{"name": "pread-with-access", "executed": true, "duration_s": 0.05663704872131348, "wasi_functions": [], "failures": []}, {"name": "fopen-with-access", "executed": true, "duration_s": 0.05728006362915039, "wasi_functions": [], "failures": []}, {"name": "clock_gettime-realtime", "executed": true, "duration_s": 0.049719810485839844, "wasi_functions": [], "failures": []}, {"name": "clock_gettime-monotonic", "executed": true, "duration_s": 0.049208879470825195, "wasi_functions": [], "failures": []}, {"name": "lseek", "executed": true, "duration_s": 0.060793399810791016, "wasi_functions": [], "failures": []}, {"name": "sock_shutdown-invalid_fd", "executed": true, "duration_s": 0.051572561264038086, "wasi_functions": [], "failures": []}, {"name": "fdopendir-with-access", "executed": true, "duration_s": 0.058042287826538086, "wasi_functions": [], "failures": []}, {"name": "clock_getres-realtime", "executed": true, "duration_s": 0.049295902252197266, "wasi_functions": [], "failures": []}, {"name": "pwrite-with-access", "executed": true, "duration_s": 0.05853676795959473, "wasi_functions": [], "failures": []}, {"name": "sock_shutdown-not_sock", "executed": true, "duration_s": 0.048624515533447266, "wasi_functions": [], "failures": ["0 == 1"]}, {"name": "clock_getres-monotonic", "executed": true, "duration_s": 0.05097842216491699, "wasi_functions": [], "failures": []}, {"name": "stat-dev-ino", "executed": true, "duration_s": 0.05933403968811035, "wasi_functions": [], "failures": []}, {"name": "fopen-with-no-access", "executed": true, "duration_s": 0.056348323822021484, "wasi_functions": [], "failures": []}]}]}