{"execution": {"start_timestamp": "2023-08-11T00:56:36.822Z", "finish_timestamp": "2023-08-11T00:56:38.972Z"}, "runtime": {"name": "wasmedge", "version": "version"}, "results": [{"name": "WASI Assemblyscript tests", "duration_s": 0.622894, "failed": 0, "skipped": 0, "passed": 12, "tests": [{"name": "environ_sizes_get-no-variables", "executed": true, "duration_s": 0.05468583106994629, "wasi_functions": [], "failures": []}, {"name": "args_get-multiple-arguments", "executed": true, "duration_s": 0.04845905303955078, "wasi_functions": [], "failures": []}, {"name": "random_get-non-zero-length", "executed": true, "duration_s": 0.06098532676696777, "wasi_functions": [], "failures": []}, {"name": "proc_exit-success", "executed": true, "duration_s": 0.04716372489929199, "wasi_functions": [], "failures": []}, {"name": "proc_exit-failure", "executed": true, "duration_s": 0.050765275955200195, "wasi_functions": [], "failures": []}, {"name": "environ_get-multiple-variables", "executed": true, "duration_s": 0.046133995056152344, "wasi_functions": [], "failures": []}, {"name": "fd_write-to-stdout", "executed": true, "duration_s": 0.07379388809204102, "wasi_functions": [], "failures": []}, {"name": "args_sizes_get-no-arguments", "executed": true, "duration_s": 0.05618453025817871, "wasi_functions": [], "failures": []}, {"name": "random_get-zero-length", "executed": true, "duration_s": 0.04483604431152344, "wasi_functions": [], "failures": []}, {"name": "fd_write-to-invalid-fd", "executed": true, "duration_s": 0.045413970947265625, "wasi_functions": [], "failures": []}, {"name": "args_sizes_get-multiple-arguments", "executed": true, "duration_s": 0.04787278175354004, "wasi_functions": [], "failures": []}, {"name": "environ_sizes_get-multiple-variables", "executed": true, "duration_s": 0.04350638389587402, "wasi_functions": [], "failures": []}]}, {"name": "WASI Rust tests", "duration_s": 0.897771, "failed": 0, "skipped": 0, "passed": 12, "tests": [{"name": "close_preopen", "executed": true, "duration_s": 0.059957265853881836, "wasi_functions": [], "failures": []}, {"name": "fd_readdir", "executed": true, "duration_s": 0.25141024589538574, "wasi_functions": [], "failures": []}, {"name": "fd_filestat_get", "executed": true, "duration_s": 0.05854392051696777, "wasi_functions": [], "failures": []}, {"name": "interesting_paths", "executed": true, "duration_s": 0.057099103927612305, "wasi_functions": [], "failures": []}, {"name": "fd_advise", "executed": true, "duration_s": 0.05982780456542969, "wasi_functions": [], "failures": []}, {"name": "dangling_fd", "executed": true, "duration_s": 0.05739450454711914, "wasi_functions": [], "failures": []}, {"name": "fd_flags_set", "executed": true, "duration_s": 0.05742335319519043, "wasi_functions": [], "failures": []}, {"name": "big_random_buf", "executed": true, "duration_s": 0.06342077255249023, "wasi_functions": [], "failures": []}, {"name": "clock_time_get", "executed": true, "duration_s": 0.05663418769836426, "wasi_functions": [], "failures": []}, {"name": "fd_filestat_set", "executed": true, "duration_s": 0.05613303184509277, "wasi_functions": [], "failures": []}, {"name": "dangling_symlink", "executed": true, "duration_s": 0.05806422233581543, "wasi_functions": [], "failures": []}, {"name": "directory_seek", "executed": true, "duration_s": 0.05864429473876953, "wasi_functions": [], "failures": []}]}, {"name": "WASI C tests", "duration_s": 0.53889, "failed": 0, "skipped": 0, "passed": 11, "tests": [{"name": "pwrite-with-access", "executed": true, "duration_s": 0.0504915714263916, "wasi_functions": [], "failures": []}, {"name": "lseek", "executed": true, "duration_s": 0.04521608352661133, "wasi_functions": [], "failures": []}, {"name": "fopen-with-no-access", "executed": true, "duration_s": 0.04922628402709961, "wasi_functions": [], "failures": []}, {"name": "fopen-with-access", "executed": true, "duration_s": 0.04352617263793945, "wasi_functions": [], "failures": []}, {"name": "stat-dev-ino", "executed": true, "duration_s": 0.05019879341125488, "wasi_functions": [], "failures": []}, {"name": "pread-with-access", "executed": true, "duration_s": 0.04695463180541992, "wasi_functions": [], "failures": []}, {"name": "clock_gettime-realtime", "executed": true, "duration_s": 0.05190753936767578, "wasi_functions": [], "failures": []}, {"name": "clock_gettime-monotonic", "executed": true, "duration_s": 0.0471494197845459, "wasi_functions": [], "failures": []}, {"name": "fdopendir-with-access", "executed": true, "duration_s": 0.05156564712524414, "wasi_functions": [], "failures": []}, {"name": "clock_getres-monotonic", "executed": true, "duration_s": 0.04555511474609375, "wasi_functions": [], "failures": []}, {"name": "clock_getres-realtime", "executed": true, "duration_s": 0.05417013168334961, "wasi_functions": [], "failures": []}]}]}