{"execution": {"start_timestamp": "2023-07-05T01:16:57.456Z", "finish_timestamp": "2023-07-05T01:17:01.291Z"}, "runtime": {"name": "wasmtime-cli", "version": "10.0.1"}, "results": [{"name": "WASI Assemblyscript tests", "duration_s": 0.649371, "failed": 0, "skipped": 0, "passed": 12, "tests": [{"name": "random_get-zero-length", "executed": true, "duration_s": 0.06088685989379883, "wasi_functions": [], "failures": []}, {"name": "proc_exit-success", "executed": true, "duration_s": 0.0545649528503418, "wasi_functions": [], "failures": []}, {"name": "args_get-multiple-arguments", "executed": true, "duration_s": 0.06371378898620605, "wasi_functions": [], "failures": []}, {"name": "proc_exit-failure", "executed": true, "duration_s": 0.0485234260559082, "wasi_functions": [], "failures": []}, {"name": "random_get-non-zero-length", "executed": true, "duration_s": 0.04901838302612305, "wasi_functions": [], "failures": []}, {"name": "fd_write-to-stdout", "executed": true, "duration_s": 0.05251193046569824, "wasi_functions": [], "failures": []}, {"name": "environ_sizes_get-no-variables", "executed": true, "duration_s": 0.04930377006530762, "wasi_functions": [], "failures": []}, {"name": "environ_get-multiple-variables", "executed": true, "duration_s": 0.05823993682861328, "wasi_functions": [], "failures": []}, {"name": "environ_sizes_get-multiple-variables", "executed": true, "duration_s": 0.04943728446960449, "wasi_functions": [], "failures": []}, {"name": "args_sizes_get-no-arguments", "executed": true, "duration_s": 0.05019378662109375, "wasi_functions": [], "failures": []}, {"name": "fd_write-to-invalid-fd", "executed": true, "duration_s": 0.050217390060424805, "wasi_functions": [], "failures": []}, {"name": "args_sizes_get-multiple-arguments", "executed": true, "duration_s": 0.05945777893066406, "wasi_functions": [], "failures": []}]}, {"name": "WASI Rust tests", "duration_s": 2.189001, "failed": 1, "skipped": 0, "passed": 11, "tests": [{"name": "close_preopen", "executed": true, "duration_s": 0.1757030487060547, "wasi_functions": [], "failures": []}, {"name": "dangling_fd", "executed": true, "duration_s": 0.18292903900146484, "wasi_functions": [], "failures": []}, {"name": "fd_readdir", "executed": true, "duration_s": 0.36213183403015137, "wasi_functions": [], "failures": []}, {"name": "big_random_buf", "executed": true, "duration_s": 0.14024853706359863, "wasi_functions": [], "failures": []}, {"name": "fd_advise", "executed": true, "duration_s": 0.18204188346862793, "wasi_functions": [], "failures": ["0 == 134"]}, {"name": "clock_time_get", "executed": true, "duration_s": 0.1357123851776123, "wasi_functions": [], "failures": []}, {"name": "fd_flags_set", "executed": true, "duration_s": 0.17526698112487793, "wasi_functions": [], "failures": []}, {"name": "fd_filestat_get", "executed": true, "duration_s": 0.14057493209838867, "wasi_functions": [], "failures": []}, {"name": "directory_seek", "executed": true, "duration_s": 0.16280531883239746, "wasi_functions": [], "failures": []}, {"name": "interesting_paths", "executed": true, "duration_s": 0.17260313034057617, "wasi_functions": [], "failures": []}, {"name": "dangling_symlink", "executed": true, "duration_s": 0.18804621696472168, "wasi_functions": [], "failures": []}, {"name": "fd_filestat_set", "executed": true, "duration_s": 0.16742944717407227, "wasi_functions": [], "failures": []}]}, {"name": "WASI C tests", "duration_s": 0.897667, "failed": 0, "skipped": 0, "passed": 11, "tests": [{"name": "clock_getres-realtime", "executed": true, "duration_s": 0.08060073852539062, "wasi_functions": [], "failures": []}, {"name": "clock_getres-monotonic", "executed": true, "duration_s": 0.07982397079467773, "wasi_functions": [], "failures": []}, {"name": "lseek", "executed": true, "duration_s": 0.08402609825134277, "wasi_functions": [], "failures": []}, {"name": "clock_gettime-realtime", "executed": true, "duration_s": 0.0694584846496582, "wasi_functions": [], "failures": []}, {"name": "fopen-with-no-access", "executed": true, "duration_s": 0.08792901039123535, "wasi_functions": [], "failures": []}, {"name": "stat-dev-ino", "executed": true, "duration_s": 0.0847315788269043, "wasi_functions": [], "failures": []}, {"name": "fopen-with-access", "executed": true, "duration_s": 0.08379101753234863, "wasi_functions": [], "failures": []}, {"name": "pwrite-with-access", "executed": true, "duration_s": 0.07963013648986816, "wasi_functions": [], "failures": []}, {"name": "clock_gettime-monotonic", "executed": true, "duration_s": 0.07498335838317871, "wasi_functions": [], "failures": []}, {"name": "pread-with-access", "executed": true, "duration_s": 0.08369278907775879, "wasi_functions": [], "failures": []}, {"name": "fdopendir-with-access", "executed": true, "duration_s": 0.08600902557373047, "wasi_functions": [], "failures": []}]}]}