{"execution": {"start_timestamp": "2024-01-12T00:59:00.801Z", "finish_timestamp": "2024-01-12T00:59:03.792Z"}, "runtime": {"name": "iwasm", "version": "1.3.0"}, "results": [{"name": "WASI Assemblyscript tests", "duration_s": 0.455379, "failed": 0, "skipped": 0, "passed": 12, "tests": [{"name": "proc_exit-failure", "executed": true, "duration_s": 0.03710627555847168, "wasi_functions": [], "failures": []}, {"name": "random_get-zero-length", "executed": true, "duration_s": 0.03787350654602051, "wasi_functions": [], "failures": []}, {"name": "random_get-non-zero-length", "executed": true, "duration_s": 0.03724861145019531, "wasi_functions": [], "failures": []}, {"name": "args_get-multiple-arguments", "executed": true, "duration_s": 0.03783845901489258, "wasi_functions": [], "failures": []}, {"name": "environ_sizes_get-no-variables", "executed": true, "duration_s": 0.03805661201477051, "wasi_functions": [], "failures": []}, {"name": "fd_write-to-invalid-fd", "executed": true, "duration_s": 0.0384366512298584, "wasi_functions": [], "failures": []}, {"name": "args_sizes_get-no-arguments", "executed": true, "duration_s": 0.03797292709350586, "wasi_functions": [], "failures": []}, {"name": "environ_get-multiple-variables", "executed": true, "duration_s": 0.0374293327331543, "wasi_functions": [], "failures": []}, {"name": "environ_sizes_get-multiple-variables", "executed": true, "duration_s": 0.036813974380493164, "wasi_functions": [], "failures": []}, {"name": "args_sizes_get-multiple-arguments", "executed": true, "duration_s": 0.03840208053588867, "wasi_functions": [], "failures": []}, {"name": "fd_write-to-stdout", "executed": true, "duration_s": 0.0379033088684082, "wasi_functions": [], "failures": []}, {"name": "proc_exit-success", "executed": true, "duration_s": 0.03777813911437988, "wasi_functions": [], "failures": []}]}, {"name": "WASI Rust tests", "duration_s": 1.978178, "failed": 0, "skipped": 0, "passed": 45, "tests": [{"name": "close_preopen", "executed": true, "duration_s": 0.044026851654052734, "wasi_functions": [], "failures": []}, {"name": "path_open_missing", "executed": true, "duration_s": 0.04209709167480469, "wasi_functions": [], "failures": []}, {"name": "overwrite_preopen", "executed": true, "duration_s": 0.04411506652832031, "wasi_functions": [], "failures": []}, {"name": "path_rename_dir_trailing_slashes", "executed": true, "duration_s": 0.0422365665435791, "wasi_functions": [], "failures": []}, {"name": "path_open_create_existing", "executed": true, "duration_s": 0.042568206787109375, "wasi_functions": [], "failures": []}, {"name": "path_link", "executed": true, "duration_s": 0.04418492317199707, "wasi_functions": [], "failures": []}, {"name": "directory_seek", "executed": true, "duration_s": 0.04422187805175781, "wasi_functions": [], "failures": []}, {"name": "interesting_paths", "executed": true, "duration_s": 0.04290318489074707, "wasi_functions": [], "failures": []}, {"name": "remove_nonempty_directory", "executed": true, "duration_s": 0.04133200645446777, "wasi_functions": [], "failures": []}, {"name": "dir_fd_op_failures", "executed": true, "duration_s": 0.04287528991699219, "wasi_functions": [], "failures": []}, {"name": "dangling_fd", "executed": true, "duration_s": 0.04307866096496582, "wasi_functions": [], "failures": []}, {"name": "big_random_buf", "executed": true, "duration_s": 0.04108142852783203, "wasi_functions": [], "failures": []}, {"name": "fd_fdstat_set_rights", "executed": true, "duration_s": 0.04273414611816406, "wasi_functions": [], "failures": []}, {"name": "fd_readdir", "executed": true, "duration_s": 0.11268234252929688, "wasi_functions": [], "failures": []}, {"name": "fd_flags_set", "executed": true, "duration_s": 0.042633056640625, "wasi_functions": [], "failures": []}, {"name": "file_seek_tell", "executed": true, "duration_s": 0.04213714599609375, "wasi_functions": [], "failures": []}, {"name": "fd_filestat_set", "executed": true, "duration_s": 0.042981624603271484, "wasi_functions": [], "failures": []}, {"name": "poll_oneoff_stdio", "executed": true, "duration_s": 0.04371023178100586, "wasi_functions": [], "failures": []}, {"name": "readlink", "executed": true, "duration_s": 0.04211902618408203, "wasi_functions": [], "failures": []}, {"name": "symlink_create", "executed": true, "duration_s": 0.04089665412902832, "wasi_functions": [], "failures": []}, {"name": "path_open_preopen", "executed": true, "duration_s": 0.04240274429321289, "wasi_functions": [], "failures": []}, {"name": "symlink_loop", "executed": true, "duration_s": 0.04189562797546387, "wasi_functions": [], "failures": []}, {"name": "path_filestat", "executed": true, "duration_s": 0.04216742515563965, "wasi_functions": [], "failures": []}, {"name": "path_open_dirfd_not_dir", "executed": true, "duration_s": 0.04082012176513672, "wasi_functions": [], "failures": []}, {"name": "file_unbuffered_write", "executed": true, "duration_s": 0.041852474212646484, "wasi_functions": [], "failures": []}, {"name": "file_allocate", "executed": true, "duration_s": 0.041811466217041016, "wasi_functions": [], "failures": []}, {"name": "file_truncation", "executed": true, "duration_s": 0.040845394134521484, "wasi_functions": [], "failures": []}, {"name": "remove_directory_trailing_slashes", "executed": true, "duration_s": 0.04231572151184082, "wasi_functions": [], "failures": []}, {"name": "sched_yield", "executed": true, "duration_s": 0.04027056694030762, "wasi_functions": [], "failures": []}, {"name": "symlink_filestat", "executed": true, "duration_s": 0.0417940616607666, "wasi_functions": [], "failures": []}, {"name": "path_symlink_trailing_slashes", "executed": true, "duration_s": 0.04312324523925781, "wasi_functions": [], "failures": []}, {"name": "stdio", "executed": true, "duration_s": 0.04177737236022949, "wasi_functions": [], "failures": []}, {"name": "truncation_rights", "executed": true, "duration_s": 0.04173111915588379, "wasi_functions": [], "failures": []}, {"name": "path_exists", "executed": true, "duration_s": 0.04191422462463379, "wasi_functions": [], "failures": []}, {"name": "clock_time_get", "executed": true, "duration_s": 0.04044485092163086, "wasi_functions": [], "failures": []}, {"name": "fd_advise", "executed": true, "duration_s": 0.04216647148132324, "wasi_functions": [], "failures": []}, {"name": "path_open_read_write", "executed": true, "duration_s": 0.04114532470703125, "wasi_functions": [], "failures": []}, {"name": "file_pread_pwrite", "executed": true, "duration_s": 0.041941165924072266, "wasi_functions": [], "failures": []}, {"name": "renumber", "executed": true, "duration_s": 0.0417478084564209, "wasi_functions": [], "failures": []}, {"name": "isatty", "executed": true, "duration_s": 0.04121804237365723, "wasi_functions": [], "failures": []}, {"name": "dangling_symlink", "executed": true, "duration_s": 0.04188251495361328, "wasi_functions": [], "failures": []}, {"name": "nofollow_errors", "executed": true, "duration_s": 0.041844844818115234, "wasi_functions": [], "failures": []}, {"name": "path_open_nonblock", "executed": true, "duration_s": 0.04113125801086426, "wasi_functions": [], "failures": []}, {"name": "path_rename", "executed": true, "duration_s": 0.04296112060546875, "wasi_functions": [], "failures": []}, {"name": "unlink_file_trailing_slashes", "executed": true, "duration_s": 0.04239630699157715, "wasi_functions": [], "failures": []}]}, {"name": "WASI C tests", "duration_s": 0.497795, "failed": 0, "skipped": 0, "passed": 13, "tests": [{"name": "sock_shutdown-invalid_fd", "executed": true, "duration_s": 0.03830885887145996, "wasi_functions": [], "failures": []}, {"name": "lseek", "executed": true, "duration_s": 0.040017127990722656, "wasi_functions": [], "failures": []}, {"name": "clock_gettime-monotonic", "executed": true, "duration_s": 0.038213253021240234, "wasi_functions": [], "failures": []}, {"name": "fdopendir-with-access", "executed": true, "duration_s": 0.038367271423339844, "wasi_functions": [], "failures": []}, {"name": "clock_getres-monotonic", "executed": true, "duration_s": 0.037456512451171875, "wasi_functions": [], "failures": []}, {"name": "pwrite-with-access", "executed": true, "duration_s": 0.03817582130432129, "wasi_functions": [], "failures": []}, {"name": "clock_gettime-realtime", "executed": true, "duration_s": 0.03766942024230957, "wasi_functions": [], "failures": []}, {"name": "clock_getres-realtime", "executed": true, "duration_s": 0.03742694854736328, "wasi_functions": [], "failures": []}, {"name": "stat-dev-ino", "executed": true, "duration_s": 0.037906646728515625, "wasi_functions": [], "failures": []}, {"name": "pread-with-access", "executed": true, "duration_s": 0.03830146789550781, "wasi_functions": [], "failures": []}, {"name": "fopen-with-access", "executed": true, "duration_s": 0.03803825378417969, "wasi_functions": [], "failures": []}, {"name": "sock_shutdown-not_sock", "executed": true, "duration_s": 0.037256479263305664, "wasi_functions": [], "failures": []}, {"name": "fopen-with-no-access", "executed": true, "duration_s": 0.038196563720703125, "wasi_functions": [], "failures": []}]}]}